Simplesender/Simplesender.py
Simplesender/__init__.py
Simplesender-0.1.0.4.dist-info/METADATA
Simplesender-0.1.0.4.dist-info/WHEEL
Simplesender-0.1.0.4.dist-info/top_level.txt
Simplesender-0.1.0.4.dist-info/RECORD
