Metadata-Version: 2.1
Name: Simplesender
Version: 0.1.0.4
Summary: Webhook 을 이용해 채널에 메시지를 보냅니다.
Home-page: https://github.com/9Hundred100Five1/simple-discordWebhook-sender
Author: 9Hundred100Five1
Author-email: ohot2124@naver.com
License: GPL-3.0
Keywords: discord,discord.py,sWs,SimpleSender
Platform: UNKNOWN
Classifier: Programming Language :: Python :: 3.7
Classifier: Programming Language :: Python :: 3.8
Classifier: Programming Language :: Python :: 3.9
Requires-Python: >=3.7
